DataPrepToolkit/__init__.py
DataPrepToolkit/data_cleaning.py
DataPrepToolkit/feature_engineering.py
DataPrepToolkit/utils.py
tests/__init__.py
tests/test_data_cleaning.py
tests/test_feature_engineering.py
DataPrepPro-0.2.0.dist-info/LICENSE.txt
DataPrepPro-0.2.0.dist-info/METADATA
DataPrepPro-0.2.0.dist-info/WHEEL
DataPrepPro-0.2.0.dist-info/top_level.txt
DataPrepPro-0.2.0.dist-info/RECORD
