Metadata-Version: 2.1
Name: DataPrepPro
Version: 0.2.0
Summary: A package for data cleaning and feature engineering
Home-page: https://github.com/CoskunErden/DataPrepToolkit
Author: Coskun Erden
Classifier: Programming Language :: Python :: 3
Classifier: License :: OSI Approved :: MIT License
Classifier: Operating System :: OS Independent
Requires-Python: >=3.6
License-File: LICENSE.txt
Requires-Dist: pandas >=1.0.0
Requires-Dist: matplotlib >=3.0.0
Requires-Dist: seaborn >=0.10.0
